atompaint/__init__.py
atompaint/callbacks.py
atompaint/checkpoints.py
atompaint/conditioning.py
atompaint/field_types.py
atompaint/layers.py
atompaint/nonlinearities.py
atompaint/pooling.py
atompaint/type_hints.py
atompaint/upsampling.py
atompaint/utils.py
atompaint/autoencoders/__init__.py
atompaint/autoencoders/asym_unet.py
atompaint/autoencoders/semisym_unet.py
atompaint/autoencoders/sym_unet.py
atompaint/autoencoders/sym_vae.py
atompaint/autoencoders/unet.py
atompaint/autoencoders/vae.py
atompaint/classifiers/__init__.py
atompaint/classifiers/amino_acid.py
atompaint/classifiers/neighbor_loc.py
atompaint/diffusion/__init__.py
atompaint/diffusion/data.py
atompaint/diffusion/ho2020.py
atompaint/diffusion/karras2022.py
atompaint/encoders/__init__.py
atompaint/encoders/asym_densenet.py
atompaint/encoders/asym_resnet.py
atompaint/encoders/encoder.py
atompaint/encoders/resnet.py
atompaint/encoders/sym_densenet.py
atompaint/encoders/sym_resnet.py
atompaint/encoders/utils.py
atompaint/end_to_end/__init__.py
atompaint/end_to_end/data.py
atompaint/end_to_end/task.py
atompaint/metrics/__init__.py
atompaint/metrics/neighbor_loc.py
atompaint/metrics/wrappers.py
atompaint/vendored/LICENSE.pytorch3d
atompaint/vendored/__init__.py
atompaint/vendored/escnn_nn_testing.py
atompaint/vendored/pytorch3d.py
atompaint-0.1.0.dist-info/licenses/LICENSE.txt
atompaint-0.1.0.dist-info/WHEEL
atompaint-0.1.0.dist-info/METADATA
atompaint-0.1.0.dist-info/RECORD
