Metadata-Version: 2.4
Name: atompaint
Version: 0.1.0
Summary: Design macromolecular interactions by in-painting full-atom models.
Author-email: Kale Kundert <kale@thekunderts.net>
Requires-Python: ~=3.10
Classifier: Programming Language :: Python :: 3
License-File: LICENSE.txt
Requires-Dist: blosum
Requires-Dist: einops
Requires-Dist: escnn_atompaint
Requires-Dist: fastdigest
Requires-Dist: lightning
Requires-Dist: macromol_dataframe
Requires-Dist: macromol_gym_pretrain
Requires-Dist: macromol_gym_unsupervised
Requires-Dist: macromol_voxelize
Requires-Dist: more_itertools
Requires-Dist: multipartial
Requires-Dist: numpy
Requires-Dist: pipeline_func
Requires-Dist: polars >= 1.17
Requires-Dist: scipy
Requires-Dist: torch
Requires-Dist: torchmetrics
Requires-Dist: torchyield
Requires-Dist: tqdm
Requires-Dist: tquiet
Requires-Dist: visible_residues
Requires-Dist: xxhash
Requires-Dist: sphinx ; extra == "doc"
Requires-Dist: sphinx_rtd_theme ; extra == "doc"
Requires-Dist: autoclasstoc ; extra == "doc"
Requires-Dist: pytest ; extra == "test"
Requires-Dist: pytest_tmp_files ; extra == "test"
Requires-Dist: pytest_unordered ; extra == "test"
Requires-Dist: parametrize_from_file ; extra == "test"
Requires-Dist: hypothesis ; extra == "test"
Requires-Dist: matplotlib ; extra == "test"
Requires-Dist: colorcet ; extra == "test"
Requires-Dist: torchtest ; extra == "test"
Project-URL: Bug Tracker, https://github.com/kalekundert/atompaint/issues
Project-URL: Continuous Integration, https://github.com/kalekundert/atompaint/actions
Project-URL: Documentation, https://atompaint.readthedocs.io/en/latest/
Project-URL: Test Coverage, https://coveralls.io/github/kalekundert/atompaint
Project-URL: Version Control, https://github.com/kalekundert/atompaint
Provides-Extra: doc
Provides-Extra: test
